setup.py
SamplePackage192940/__init__.py
SamplePackage192940/echo.py
SamplePackage192940/is_null.py
SamplePackage192940.egg-info/PKG-INFO
SamplePackage192940.egg-info/SOURCES.txt
SamplePackage192940.egg-info/dependency_links.txt
SamplePackage192940.egg-info/not-zip-safe
SamplePackage192940.egg-info/requires.txt
SamplePackage192940.egg-info/top_level.txt